dirwalker
