Metadata-Version: 1.1
Name: dirwalker
Version: 0.2
Summary: Python Directory Walker module
Home-page: https://github.com/matthewrankin/dirwalker
Author: Matthew Rankin
Author-email: matthew@questrail.com
License: MIT
Platform: UNKNOWN
Classifier: Programming Language :: Python
Classifier: Programming Language :: Python :: 3
Classifier: License :: OSI Approved :: MIT License
Classifier: Development Status :: 3 - Alpha
Classifier: Operating System :: OS Independent
Classifier: Intended Audience :: Developers
Classifier: Topic :: Software Development :: Libraries :: Python Modules
